hydropt/__init__.py
hydropt/action.py
hydropt/constraints.py
hydropt/core.py
hydropt/model.py
hydropt/scenarios.py
hydropt/utils.py
hydropt/data/spot_prices_2019.csv
hydropt-0.0.3.dist-info/LICENSE
hydropt-0.0.3.dist-info/METADATA
hydropt-0.0.3.dist-info/WHEEL
hydropt-0.0.3.dist-info/top_level.txt
hydropt-0.0.3.dist-info/RECORD
