Metadata-Version: 2.1
Name: hydropt
Version: 0.0.3
Summary: Solves dynamical programming problems for the optimization of hydro power plants.
Home-page: https://github.com/yenzmike/hydropt
Author: Jens Boss
Author-email: bossjens@gmail.com
License: UNKNOWN
Platform: UNKNOWN
Classifier: Programming Language :: Python :: 3
Classifier: License :: OSI Approved :: MIT License
Classifier: Operating System :: OS Independent
Requires-Python: >=3.7
Requires-Dist: pandas (>=0.25.3)
Requires-Dist: numpy (>=1.17.4)
Requires-Dist: scipy (>=1.5.0)
Requires-Dist: matplotlib (>=3.1.1)
Provides-Extra: dev
Requires-Dist: pytest (>=5.4.2) ; extra == 'dev'
